orgpedia/__init__.py
orgpedia/components/__init__.py
orgpedia/components/details_merger.py
orgpedia/components/hindi_order_builder.py
orgpedia/components/hindi_order_tagger.py
orgpedia/components/id_assigner.py
orgpedia/components/id_assigner_fields.py
orgpedia/components/order_builder.py
orgpedia/components/order_tagger.py
orgpedia/components/pdforder_builder.py
orgpedia/components/pdfpost_parser.py
orgpedia/components/post_parser.py
orgpedia/components/table_order_builder.py
orgpedia/components/tenure_builder.py
orgpedia/components/website_gen.py
orgpedia/extracts/orgpedia.py
orgpedia-0.1.1.dist-info/WHEEL
orgpedia-0.1.1.dist-info/METADATA
orgpedia-0.1.1.dist-info/RECORD
